niutils/__init__.py
niutils/_version.py
niutils/niutils.py
niutils/cli/__init__.py
niutils/tests/__init__.py
niutils-0.9.0.dist-info/LICENSE
niutils-0.9.0.dist-info/METADATA
niutils-0.9.0.dist-info/WHEEL
niutils-0.9.0.dist-info/entry_points.txt
niutils-0.9.0.dist-info/top_level.txt
niutils-0.9.0.dist-info/RECORD
