Metadata-Version: 2.1
Name: niutils
Version: 0.9.0
Summary: Various utilities to fast-track some boring python coding.
Home-page: https://github.com/smoia/niutils
Author: niutils developers
Maintainer: Stefano Moia
Maintainer-email: s.moia@bcbl.eu
License: Apache-2.0
Download-URL: https://github.com/smoia/niutils
Platform: OS Independent
Classifier: Development Status :: 1 - Planning
Classifier: Intended Audience :: Science/Research
Classifier: License :: OSI Approved :: Apache Software License
Classifier: Programming Language :: Python :: 3.6
Classifier: Programming Language :: Python :: 3.7
Provides: niutils
Requires-Python: >=3.6.1
Requires-Dist: nibabel
Requires-Dist: numpy (>=1.9.3)
Requires-Dist: matplotlib (>=3.1.1)
Provides-Extra: all
Requires-Dist: scipy ; extra == 'all'
Requires-Dist: scikit-learn ; extra == 'all'
Requires-Dist: scikit-image ; extra == 'all'
Provides-Extra: clustering
Requires-Dist: scipy ; extra == 'clustering'
Requires-Dist: scikit-learn ; extra == 'clustering'
Requires-Dist: scikit-image ; extra == 'clustering'
Provides-Extra: dev
Requires-Dist: scipy ; extra == 'dev'
Requires-Dist: scikit-learn ; extra == 'dev'
Requires-Dist: scikit-image ; extra == 'dev'
Requires-Dist: pytest (>=5.3) ; extra == 'dev'
Requires-Dist: pytest-cov ; extra == 'dev'
Requires-Dist: flake8 (>=3.7) ; extra == 'dev'
Requires-Dist: flake8-docstrings (>=1.5) ; extra == 'dev'
Provides-Extra: style
Requires-Dist: flake8 (>=3.7) ; extra == 'style'
Requires-Dist: flake8-docstrings (>=1.5) ; extra == 'style'
Provides-Extra: test
Requires-Dist: pytest (>=5.3) ; extra == 'test'
Requires-Dist: pytest-cov ; extra == 'test'
Requires-Dist: flake8 (>=3.7) ; extra == 'test'
Requires-Dist: flake8-docstrings (>=1.5) ; extra == 'test'
